{
	"name": "dataflow2",
	"properties": {
		"type": "MappingDataFlow",
		"typeProperties": {
			"sources": [
				{
					"dataset": {
						"referenceName": "DS_BLOB_CSV_FILE_GENERIC",
						"type": "DatasetReference"
					},
					"name": "sourceproduct"
				},
				{
					"dataset": {
						"referenceName": "DS_BLOB_CSV_FILE_GENERIC",
						"type": "DatasetReference"
					},
					"name": "sourceproductcategory"
				}
			],
			"sinks": [],
			"transformations": [],
			"scriptLines": [
				"source(allowSchemaDrift: true,",
				"     validateSchema: false,",
				"     ignoreNoFilesFound: false) ~> sourceproduct",
				"source(allowSchemaDrift: true,",
				"     validateSchema: false,",
				"     ignoreNoFilesFound: false) ~> sourceproductcategory"
			]
		}
	}
}